smooth_knn/__init__.py
smooth_knn/classifier.py
smooth_knn-0.0.4.dist-info/METADATA
smooth_knn-0.0.4.dist-info/WHEEL
smooth_knn-0.0.4.dist-info/licenses/LICENSE
smooth_knn-0.0.4.dist-info/RECORD
